fpilot/__init__.py
fpilot/training/__init__.py
fpilot/training/trainer.py
fpilot/utils/__init__.py
fpilot/utils/checkpoint_utils.py
fpilot/utils/common_utils.py
fpilot/utils/opt_utils.py
fpilot/utils/tracker_utils.py
fpilot/utils/trainer_utils.py
flax_pilot-0.2.3.dist-info/LICENSE
flax_pilot-0.2.3.dist-info/METADATA
flax_pilot-0.2.3.dist-info/WHEEL
flax_pilot-0.2.3.dist-info/top_level.txt
flax_pilot-0.2.3.dist-info/RECORD
