Metadata-Version: 2.1
Name: flax-pilot
Version: 0.2.3
Summary: A Simplistic trainer for Flax
Home-page: https://github.com/NITHISHM2410/flax-pilot
Author: Nithish M
Author-email: nithishm2206@gmail.com
Classifier: Programming Language :: Python :: 3.10
Classifier: License :: OSI Approved :: MIT License
Requires-Python: >=3.10
License-File: LICENSE
Requires-Dist: jax[cuda12]==0.4.37
Requires-Dist: flax>=0.10.2
Requires-Dist: optax>=0.2.4
Requires-Dist: numpy
Requires-Dist: tqdm
Requires-Dist: mergedeep
Requires-Dist: orbax-checkpoint>=0.5.20
